tinymm/__init__.py
tinymm/model_config.py
tinymm/ALBEF/dataset.py
tinymm/ALBEF/model.py
tinymm/ALBEF/provider.py
tinymm/CLIP/dataset.py
tinymm/CLIP/evaluate.py
tinymm/CLIP/model.py
tinymm/CLIP/provider.py
tinymm/GPT/model.py
tinymm/MLM/dataset.py
tinymm/MLM/model.py
tinymm/MLM/provider.py
utils/extract_enwiki.py
utils/extract_tars.py
tinymm-0.10.dist-info/LICENSE
tinymm-0.10.dist-info/METADATA
tinymm-0.10.dist-info/WHEEL
tinymm-0.10.dist-info/top_level.txt
tinymm-0.10.dist-info/RECORD
