Metadata-Version: 2.1
Name: tinymm
Version: 0.10
Summary: A simple and 'tiny' implementation of many multimodal models
Author: Robin Dong
License: MIT License
Keywords: Vision-Language,Multimodal,Deep Learning,Library,PyTorch
Requires-Python: >=3.8.0
License-File: LICENSE
Requires-Dist: fire
Requires-Dist: torch
Requires-Dist: timm
Requires-Dist: tiktoken
Requires-Dist: opencv-python
